Workbook

Sheet Debit Transactions
A1: FY | B1: Date | C1: Month | D1: Merchant / Details | E1: Amount (INR) | F1: Bucket
A2: FY2024-25 | B2: 45383 | C2: Apr-2024 | D2: Paid to Fresh Signature Bhubaneshwar 2553 | E2: 58.8 | F2: =IF(E2>500,"Above 500","500 & Below") -> 500 & Below
A3: FY2024-25 | B3: 45383 | C3: Apr-2024 | D3: Paid to Fresh Signature Bhubaneshwar 2553 | E3: 359.49 | F3: =IF(E3>500,"Above 500","500 & Below") -> 500 & Below
A4: FY2024-25 | B4: 45383 | C4: Apr-2024 | D4: Paid to Fresh Signature Bhubaneshwar 2553 | E4: 19.6 | F4: =IF(E4>500,"Above 500","500 & Below") -> 500 & Below
A5: FY2024-25 | B5: 45383 | C5: Apr-2024 | D5: Paid to Sitanath jena | E5: 30 | F5: =IF(E5>500,"Above 500","500 & Below") -> 500 & Below
A6: FY2024-25 | B6: 45383 | C6: Apr-2024 | D6: Paid to CAPITAL REGION URBAN TRANSPORT | E6: 45 | F6: =IF(E6>500,"Above 500","500 & Below") -> 500 & Below
A7: FY2024-25 | B7: 45383 | C7: Apr-2024 | D7: Paid to HOTEL SHREE VINEETH'S | E7: 775 | F7: =IF(E7>500,"Above 500","500 & Below") -> Above 500
A8: FY2024-25 | B8: 45383 | C8: Apr-2024 | D8: Paid to CAPITAL REGION URBAN TRANSPORT | E8: 30 | F8: =IF(E8>500,"Above 500","500 & Below") -> 500 & Below
A9: FY2024-25 | B9: 45385 | C9: Apr-2024 | D9: Paid to ******9891 | E9: 200 | F9: =IF(E9>500,"Above 500","500 & Below") -> 500 & Below
A10: FY2024-25 | B10: 45385 | C10: Apr-2024 | D10: Paid to Mrutyunjay Sahoo | E10: 1 | F10: =IF(E10>500,"Above 500","500 & Below") -> 500 & Below
A11: FY2024-25 | B11: 45389 | C11: Apr-2024 | D11: Paid to Mr SUSANTA MOHAPAT | E11: 60 | F11: =IF(E11>500,"Above 500","500 & Below") -> 500 & Below
A12: FY2024-25 | B12: 45390 | C12: Apr-2024 | D12: Paid to Anil Kumar Dash | E12: 2000 | F12: =IF(E12>500,"Above 500","500 & Below") -> Above 500
A13: FY2024-25 | B13: 45393 | C13: Apr-2024 | D13: Paid to Airtel Prepaid Recharges | E13: 265 | F13: =IF(E13>500,"Above 500","500 & Below") -> 500 & Below
... A2395: FY2025-26 | B2395: 46112 | C2395: Mar-2026 | D2395: Paid to ANJAN KUMAR DAS | E2395: 20 | F2395: =IF(E2395>500,"Above 500","500 & Below") -> 500 & Below

Sheet Summary
A1: Debit Spend Summary — Above vs Below INR 500, by Financial Year
A3: Financial Year | B3: Bucket | C3: Transaction Count | D3: Total Amount (INR) | E3: Average Amount (INR) | F3: % of FY Debit Spend
A4: FY2024-25 | B4: Above 500 | C4: =COUNTIFS('Debit Transactions'!$A$2:$A$2395,$A4,'Debit Transactions'!$F$2:$F$2395,$B4) -> 197 | D4: =SUMIFS('Debit Transactions'!$E$2:$E$2395,'Debit Transactions'!$A$2:$A$2395,$A4,'Debit Transactions'!$F$2:$F$2395,$B4) -> 475236.92 | E4: =IFERROR(D4/C4,0) -> 2412.3702 | F4: =IFERROR(D4/D6,0) -> 0.81319307
A5: FY2024-25 | B5: 500 & Below | C5: =COUNTIFS('Debit Transactions'!$A$2:$A$2395,$A5,'Debit Transactions'!$F$2:$F$2395,$B5) -> 863 | D5: =SUMIFS('Debit Transactions'!$E$2:$E$2395,'Debit Transactions'!$A$2:$A$2395,$A5,'Debit Transactions'!$F$2:$F$2395,$B5) -> 109171.55 | E5: =IFERROR(D5/C5,0) -> 126.50238 | F5: =IFERROR(D5/D6,0) -> 0.18680693
A6: FY2024-25 | B6: FY Total | C6: =SUM(C4:C5) -> 1060 | D6: =SUM(D4:D5) -> 584408.47 | E6: =IFERROR(D6/C6,0) -> 551.32875 | F6: 1
A7: FY2025-26 | B7: Above 500 | C7: =COUNTIFS('Debit Transactions'!$A$2:$A$2395,$A7,'Debit Transactions'!$F$2:$F$2395,$B7) -> 207 | D7: =SUMIFS('Debit Transactions'!$E$2:$E$2395,'Debit Transactions'!$A$2:$A$2395,$A7,'Debit Transactions'!$F$2:$F$2395,$B7) -> 398033.31 | E7: =IFERROR(D7/C7,0) -> 1922.8662 | F7: =IFERROR(D7/D9,0) -> 0.74276377
A8: FY2025-26 | B8: 500 & Below | C8: =COUNTIFS('Debit Transactions'!$A$2:$A$2395,$A8,'Debit Transactions'!$F$2:$F$2395,$B8) -> 1127 | D8: =SUMIFS('Debit Transactions'!$E$2:$E$2395,'Debit Transactions'!$A$2:$A$2395,$A8,'Debit Transactions'!$F$2:$F$2395,$B8) -> 137848.12 | E8: =IFERROR(D8/C8,0) -> 122.31421 | F8: =IFERROR(D8/D9,0) -> 0.25723623
A9: FY2025-26 | B9: FY Total | C9: =SUM(C7:C8) -> 1334 | D9: =SUM(D7:D8) -> 535881.43 | E9: =IFERROR(D9/C9,0) -> 401.71022 | F9: 1
A11: Grand Total (Both FY) | C11: =C6+C9 -> 2394 | D11: =D6+D9 -> 1120289.9
A13: =AVERAGE(D5,D8) -> 123509.84 | B13: =SQRT((2*A13*0.3)/0.025) -> 1721.6957
A14: =A13/12 -> 10292.486

Sheet Monthly Breakdown
A1: Monthly Debit Spend by Bucket
A3: Financial Year | B3: Month | C3: Above 500 - Count | D3: Above 500 - Amount | E3: 500 & Below - Count | F3: 500 & Below - Amount | G3: Total Amount
A4: FY2024-25 | B4: Apr-2024 | C4: =COUNTIFS('Debit Transactions'!$A$2:$A$2395,$A4,'Debit Transactions'!$C$2:$C$2395,$B4,'Debit Transactions'!$F$2:$F$2395,"Above 500") -> 7 | D4: =SUMIFS('Debit Transactions'!$E$2:$E$2395,'Debit Transactions'!$A$2:$A$2395,$A4,'Debit Transactions'!$C$2:$C$2395,$B4,'Debit Transactions'!$F$2:$F$2395,"Above 500") -> 12814 | E4: =COUNTIFS('Debit Transactions'!$A$2:$A$2395,$A4,'Debit Transactions'!$C$2:$C$2395,$B4,'Debit Transactions'!$F$2:$F$2395,"500 & Below") -> 35 | F4: =SUMIFS('Debit Transactions'!$E$2:$E$2395,'Debit Transactions'!$A$2:$A$2395,$A4,'Debit Transactions'!$C$2:$C$2395,$B4,'Debit Transactions'!$F$2:$F$2395,"500 & Below") -> 3485.89 | G4: =D4+F4 -> 16299.89
A5: FY2024-25 | B5: May-2024 | C5: =COUNTIFS('Debit Transactions'!$A$2:$A$2395,$A5,'Debit Transactions'!$C$2:$C$2395,$B5,'Debit Transactions'!$F$2:$F$2395,"Above 500") -> 17 | D5: =SUMIFS('Debit Transactions'!$E$2:$E$2395,'Debit Transactions'!$A$2:$A$2395,$A5,'Debit Transactions'!$C$2:$C$2395,$B5,'Debit Transactions'!$F$2:$F$2395,"Above 500") -> 40808.8 | E5: =COUNTIFS('Debit Transactions'!$A$2:$A$2395,$A5,'Debit Transactions'!$C$2:$C$2395,$B5,'Debit Transactions'!$F$2:$F$2395,"500 & Below") -> 33 | F5: =SUMIFS('Debit Transactions'!$E$2:$E$2395,'Debit Transactions'!$A$2:$A$2395,$A5,'Debit Transactions'!$C$2:$C$2395,$B5,'Debit Transactions'!$F$2:$F$2395,"500 & Below") -> 4037 | G5: =D5+F5 -> 44845.8
A6: FY2024-25 | B6: Jun-2024 | C6: =COUNTIFS('Debit Transactions'!$A$2:$A$2395,$A6,'Debit Transactions'!$C$2:$C$2395,$B6,'Debit Transactions'!$F$2:$F$2395,"Above 500") -> 14 | D6: =SUMIFS('Debit Transactions'!$E$2:$E$2395,'Debit Transactions'!$A$2:$A$2395,$A6,'Debit Transactions'!$C$2:$C$2395,$B6,'Debit Transactions'!$F$2:$F$2395,"Above 500") -> 24251.58 | E6: =COUNTIFS('Debit Transactions'!$A$2:$A$2395,$A6,'Debit Transactions'!$C$2:$C$2395,$B6,'Debit Transactions'!$F$2:$F$2395,"500 & Below") -> 61 | F6: =SUMIFS('Debit Transactions'!$E$2:$E$2395,'Debit Transactions'!$A$2:$A$2395,$A6,'Debit Transactions'!$C$2:$C$2395,$B6,'Debit Transactions'!$F$2:$F$2395,"500 & Below") -> 8457.8 | G6: =D6+F6 -> 32709.38
A7: FY2024-25 | B7: Jul-2024 | C7: =COUNTIFS('Debit Transactions'!$A$2:$A$2395,$A7,'Debit Transactions'!$C$2:$C$2395,$B7,'Debit Transactions'!$F$2:$F$2395,"Above 500") -> 17 | D7: =SUMIFS('Debit Transactions'!$E$2:$E$2395,'Debit Transactions'!$A$2:$A$2395,$A7,'Debit Transactions'!$C$2:$C$2395,$B7,'Debit Transactions'!$F$2:$F$2395,"Above 500") -> 36470.49 | E7: =COUNTIFS('Debit Transactions'!$A$2:$A$2395,$A7,'Debit Transactions'!$C$2:$C$2395,$B7,'Debit Transactions'!$F$2:$F$2395,"500 & Below") -> 78 | F7: =SUMIFS('Debit Transactions'!$E$2:$E$2395,'Debit Transactions'!$A$2:$A$2395,$A7,'Debit Transactions'!$C$2:$C$2395,$B7,'Debit Transactions'!$F$2:$F$2395,"500 & Below") -> 8636.77 | G7: =D7+F7 -> 45107.26
A8: FY2024-25 | B8: Aug-2024 | C8: =COUNTIFS('Debit Transactions'!$A$2:$A$2395,$A8,'Debit Transactions'!$C$2:$C$2395,$B8,'Debit Transactions'!$F$2:$F$2395,"Above 500") -> 25 | D8: =SUMIFS('Debit Transactions'!$E$2:$E$2395,'Debit Transactions'!$A$2:$A$2395,$A8,'Debit Transactions'!$C$2:$C$2395,$B8,'Debit Transactions'!$F$2:$F$2395,"Above 500") -> 35688.36 | E8: =COUNTIFS('Debit Transactions'!$A$2:$A$2395,$A8,'Debit Transactions'!$C$2:$C$2395,$B8,'Debit Transactions'!$F$2:$F$2395,"500 & Below") -> 98 | F8: =SUMIFS('Debit Transactions'!$E$2:$E$2395,'Debit Transactions'!$A$2:$A$2395,$A8,'Debit Transactions'!$C$2:$C$2395,$B8,'Debit Transactions'!$F$2:$F$2395,"500 & Below") -> 11876.76 | G8: =D8+F8 -> 47565.12
A9: FY2024-25 | B9: Sep-2024 | C9: =COUNTIFS('Debit Transactions'!$A$2:$A$2395,$A9,'Debit Transactions'!$C$2:$C$2395,$B9,'Debit Transactions'!$F$2:$F$2395,"Above 500") -> 18 | D9: =SUMIFS('Debit Transactions'!$E$2:$E$2395,'Debit Transactions'!$A$2:$A$2395,$A9,'Debit Transactions'!$C$2:$C$2395,$B9,'Debit Transactions'!$F$2:$F$2395,"Above 500") -> 78034 | E9: =COUNTIFS('Debit Transactions'!$A$2:$A$2395,$A9,'Debit Transactions'!$C$2:$C$2395,$B9,'Debit Transactions'!$F$2:$F$2395,"500 & Below") -> 96 | F9: =SUMIFS('Debit Transactions'!$E$2:$E$2395,'Debit Transactions'!$A$2:$A$2395,$A9,'Debit Transactions'!$C$2:$C$2395,$B9,'Debit Transactions'!$F$2:$F$2395,"500 & Below") -> 9569.17 | G9: =D9+F9 -> 87603.17
A10: FY2024-25 | B10: Oct-2024 | C10: =COUNTIFS('Debit Transactions'!$A$2:$A$2395,$A10,'Debit Transactions'!$C$2:$C$2395,$B10,'Debit Transactions'!$F$2:$F$2395,"Above 500") -> 17 | D10: =SUMIFS('Debit Transactions'!$E$2:$E$2395,'Debit Transactions'!$A$2:$A$2395,$A10,'Debit Transactions'!$C$2:$C$2395,$B10,'Debit Transactions'!$F$2:$F$2395,"Above 500") -> 61117.18 | E10: =COUNTIFS('Debit Transactions'!$A$2:$A$2395,$A10,'Debit Transactions'!$C$2:$C$2395,$B10,'Debit Transactions'!$F$2:$F$2395,"500 & Below") -> 84 | F10: =SUMIFS('Debit Transactions'!$E$2:$E$2395,'Debit Transactions'!$A$2:$A$2395,$A10,'Debit Transactions'!$C$2:$C$2395,$B10,'Debit Transactions'!$F$2:$F$2395,"500 & Below") -> 13885.58 | G10: =D10+F10 -> 75002.76
A11: FY2024-25 | B11: Nov-2024 | C11: =COUNTIFS('Debit Transactions'!$A$2:$A$2395,$A11,'Debit Transactions'!$C$2:$C$2395,$B11,'Debit Transactions'!$F$2:$F$2395,"Above 500") -> 21 | D11: =SUMIFS('Debit Transactions'!$E$2:$E$2395,'Debit Transactions'!$A$2:$A$2395,$A11,'Debit Transactions'!$C$2:$C$2395,$B11,'Debit Transactions'!$F$2:$F$2395,"Above 500") -> 62155 | E11: =COUNTIFS('Debit Transactions'!$A$2:$A$2395,$A11,'Debit Transactions'!$C$2:$C$2395,$B11,'Debit Transactions'!$F$2:$F$2395,"500 & Below") -> 79 | F11: =SUMIFS('Debit Transactions'!$E$2:$E$2395,'Debit Transactions'!$A$2:$A$2395,$A11,'Debit Transactions'!$C$2:$C$2395,$B11,'Debit Transactions'!$F$2:$F$2395,"500 & Below") -> 10806.52 | G11: =D11+F11 -> 72961.52
A12: FY2024-25 | B12: Dec-2024 | C12: =COUNTIFS('Debit Transactions'!$A$2:$A$2395,$A12,'Debit Transactions'!$C$2:$C$2395,$B12,'Debit Transactions'!$F$2:$F$2395,"Above 500") -> 11 | D12: =SUMIFS('Debit Transactions'!$E$2:$E$2395,'Debit Transactions'!$A$2:$A$2395,$A12,'Debit Transactions'!$C$2:$C$2395,$B12,'Debit Transactions'!$F$2:$F$2395,"Above 500") -> 13363 | E12: =COUNTIFS('Debit Transactions'!$A$2:$A$2395,$A12,'Debit Transactions'!$C$2:$C$2395,$B12,'Debit Transactions'!$F$2:$F$2395,"500 & Below") -> 78 | F12: =SUMIFS('Debit Transactions'!$E$2:$E$2395,'Debit Transactions'!$A$2:$A$2395,$A12,'Debit Transactions'!$C$2:$C$2395,$B12,'Debit Transactions'!$F$2:$F$2395,"500 & Below") -> 9668 | G12: =D12+F12 -> 23031
A13: FY2024-25 | B13: Jan-2025 | C13: =COUNTIFS('Debit Transactions'!$A$2:$A$2395,$A13,'Debit Transactions'!$C$2:$C$2395,$B13,'Debit Transactions'!$F$2:$F$2395,"Above 500") -> 13 | D13: =SUMIFS('Debit Transactions'!$E$2:$E$2395,'Debit Transactions'!$A$2:$A$2395,$A13,'Debit Transactions'!$C$2:$C$2395,$B13,'Debit Transactions'!$F$2:$F$2395,"Above 500") -> 18571 | E13: =COUNTIFS('Debit Transactions'!$A$2:$A$2395,$A13,'Debit Transactions'!$C$2:$C$2395,$B13,'Debit Transactions'!$F$2:$F$2395,"500 & Below") -> 85 | F13: =SUMIFS('Debit Transactions'!$E$2:$E$2395,'Debit Transactions'!$A$2:$A$2395,$A13,'Debit Transactions'!$C$2:$C$2395,$B13,'Debit Transactions'!$F$2:$F$2395,"500 & Below") -> 11779.71 | G13: =D13+F13 -> 30350.71
A14: FY2024-25 | B14: Feb-2025 | C14: =COUNTIFS('Debit Transactions'!$A$2:$A$2395,$A14,'Debit Transactions'!$C$2:$C$2395,$B14,'Debit Transactions'!$F$2:$F$2395,"Above 500") -> 19 | D14: =SUMIFS('Debit Transactions'!$E$2:$E$2395,'Debit Transactions'!$A$2:$A$2395,$A14,'Debit Transactions'!$C$2:$C$2395,$B14,'Debit Transactions'!$F$2:$F$2395,"Above 500") -> 48620.41 | E14: =COUNTIFS('Debit Transactions'!$A$2:$A$2395,$A14,'Debit Transactions'!$C$2:$C$2395,$B14,'Debit Transactions'!$F$2:$F$2395,"500 & Below") -> 75 | F14: =SUMIFS('Debit Transactions'!$E$2:$E$2395,'Debit Transactions'!$A$2:$A$2395,$A14,'Debit Transactions'!$C$2:$C$2395,$B14,'Debit Transactions'!$F$2:$F$2395,"500 & Below") -> 9537.15 | G14: =D14+F14 -> 58157.56
A15: FY2024-25 | B15: Mar-2025 | C15: =COUNTIFS('Debit Transactions'!$A$2:$A$2395,$A15,'Debit Transactions'!$C$2:$C$2395,$B15,'Debit Transactions'!$F$2:$F$2395,"Above 500") -> 18 | D15: =SUMIFS('Debit Transactions'!$E$2:$E$2395,'Debit Transactions'!$A$2:$A$2395,$A15,'Debit Transactions'!$C$2:$C$2395,$B15,'Debit Transactions'!$F$2:$F$2395,"Above 500") -> 43343.1 | E15: =COUNTIFS('Debit Transactions'!$A$2:$A$2395,$A15,'Debit Transactions'!$C$2:$C$2395,$B15,'Debit Transactions'!$F$2:$F$2395,"500 & Below") -> 61 | F15: =SUMIFS('Debit Transactions'!$E$2:$E$2395,'Debit Transactions'!$A$2:$A$2395,$A15,'Debit Transactions'!$C$2:$C$2395,$B15,'Debit Transactions'!$F$2:$F$2395,"500 & Below") -> 7431.2 | G15: =D15+F15 -> 50774.3
... A27: FY2025-26 | B27: Mar-2026 | C27: =COUNTIFS('Debit Transactions'!$A$2:$A$2395,$A27,'Debit Transactions'!$C$2:$C$2395,$B27,'Debit Transactions'!$F$2:$F$2395,"Above 500") -> 15 | D27: =SUMIFS('Debit Transactions'!$E$2:$E$2395,'Debit Transactions'!$A$2:$A$2395,$A27,'Debit Transactions'!$C$2:$C$2395,$B27,'Debit Transactions'!$F$2:$F$2395,"Above 500") -> 28343 | E27: =COUNTIFS('Debit Transactions'!$A$2:$A$2395,$A27,'Debit Transactions'!$C$2:$C$2395,$B27,'Debit Transactions'!$F$2:$F$2395,"500 & Below") -> 64 | F27: =SUMIFS('Debit Transactions'!$E$2:$E$2395,'Debit Transactions'!$A$2:$A$2395,$A27,'Debit Transactions'!$C$2:$C$2395,$B27,'Debit Transactions'!$F$2:$F$2395,"500 & Below") -> 9740.64 | G27: =D27+F27 -> 38083.64

Sheet FY 25 Summary
A1: Bucket | B1: Total Transactions | C1: Total Value (INR)
A2: Above 500 | B2: =COUNTIFS('Debit Transactions'!A:A, "FY2024-25", 'Debit Transactions'!F:F, A2) -> 197 | C2: =SUMIFS('Debit Transactions'!E:E, 'Debit Transactions'!A:A, "FY2024-25", 'Debit Transactions'!F:F, A2) -> 475236.92
A3: 500 & Below | B3: =COUNTIFS('Debit Transactions'!A:A, "FY2024-25", 'Debit Transactions'!F:F, A3) -> 863 | C3: =SUMIFS('Debit Transactions'!E:E, 'Debit Transactions'!A:A, "FY2024-25", 'Debit Transactions'!F:F, A3) -> 109171.55

Sheet FY 26 Summary
A1: Bucket | B1: Total Transactions | C1: Total Value (INR)
A2: Above 500 | B2: =COUNTIFS('Debit Transactions'!A:A, "FY2025-26", 'Debit Transactions'!F:F, A2) -> 207 | C2: =SUMIFS('Debit Transactions'!E:E, 'Debit Transactions'!A:A, "FY2025-26", 'Debit Transactions'!F:F, A2) -> 398033.31
A3: 500 & Below | B3: =COUNTIFS('Debit Transactions'!A:A, "FY2025-26", 'Debit Transactions'!F:F, A3) -> 1127 | C3: =SUMIFS('Debit Transactions'!E:E, 'Debit Transactions'!A:A, "FY2025-26", 'Debit Transactions'!F:F, A3) -> 137848.12

Sheet IT Questions for Quiz
A1: Q# | B1: Topic | C1: Question Description | D1: Option A | E1: Option B | F1: Option C | G1: Option D | H1: Correct Option
A2: SECTION: WORD
A3: 1 | B3: Word | C3: In Word, Page layout tab includes | D3: Create | E3: Show | F3: Paragraph | G3: Tables | H3: C
A4: 2 | B4: Word | C4: Page Setup group includes _________options. | D4: Orientation | E4: Breaks | F4: Hyphenation | G4: All of These | H4: D
A5: 3 | B5: Word | C5: Margins define the amount of _________ that appears at the top, bottom, left and right edges of our document. | D5: Extra space | E5: White space | F5: Blank space | G5: No space | H5: B
A6: 4 | B6: Word | C6: _________ margin setting adds extra space to the side margin or top margin of a document that we plan to bind. | D6: Page | E6: Gutter | F6: Semi Extra | G6: Adjust | H6: B
A7: 5 | B7: Word | C7: Portrait means _________ | D7: Vertical | E7: Horizontal | F7: Both A and B | G7: Nither A Nor B | H7: A
A8: 6 | B8: Word | C8: Business correspondence uses the default page size in Word. | D8: 8 1/2 by 11 | E8: 8 1/2 by 10 | F8: 8 1/4 by 10 | G8: None | H8: A
A9: 7 | B9: Word | C9: In News letters _________ option is used to splits the text into two or more areas and also available in word. | D9: Row | E9: Columns | F9: Both A and B | G9: Nither A Nor B | H9: B
A10: 8 | B10: Word | C10: What feature in word allows you to track changes made to a document | D10: track change | E10: comments | F10: document inspector | G10: compare | H10: A
A11: 9 | B11: Word | C11: _________ Section break inserts the section break and then starts the new section on the next odd or even numbered page. | D11: Even or Odd | E11: Continuous | F11: Next Page | G11: New Page | H11: A
A12: 10 | B12: Word | C12: According to Add line numbers, Table is counted as one line. | D12: TRUE | E12: FALSE | F12: Can't Say | G12: None | H12: A
A13: 11 | B13: Word | C13: Ctrl + A is used for | D13: Delet All | E13: Select All | F13: Unselect All | G13: None | H13: B
A14: 12 | B14: Word | C14: Which of the following sortcuts will bold the selected text | D14: CTRL+ B | E14: CTRL+I | F14: CTRL+ U | G14: CTRL+ E | H14: A
A15: 13 | B15: Word | C15: Page Background includes | D15: Watermark | E15: Page Color | F15: Page Borders | G15: All of These | H15: D
A16: 14 | B16: Word | C16: Text flows around the image and hugs its shape. | D16: Tight | E16: Through | F16: Behind Text | G16: None | H16: A
A17: 15 | B17: Word | C17: In word, which view is best for reading a document without distractions | D17: Prient layout | E17: Web layout | F17: Read mode | G17: Outline view | H17: C
A18: 16 | B18: Word | C18: Mailing Tab includes | D18: Create | E18: Start Mail Merge | F18: Preview Results | G18: All of These | H18: D
A19: 17 | B19: Word | C19: Create Group includes | D19: Envelopes | E19: Labels | F19: Both A and B | G19: Nither A Nor B | H19: C
A20: 18 | B20: Word | C20: Start Mail Merge group includes | D20: Start Mail Merge | E20: Select Recipients | F20: Edit Recipient List | G20: All of These | H20: D
A21: 19 | B21: Word | C21: Mail Merge Data Base list extension is | D21: .accdb | E21: .mdb | F21: Both A and B | G21: Nither A Nor B | H21: B
A22: 20 | B22: Word | C22: Address block appears which dialoge box? | D22: Insert Address block | E22: Address block | F22: Field Block | G22: None | H22: A
A23: 21 | B23: Word | C23: REFERENCES TAB includes | D23: Table of Contents | E23: Captions | F23: Both A and B | G23: Nither A Nor B | H23: C
A24: 22 | B24: Word | C24: Table of Contents Group not includes | D24: Table of Contents | E24: Add Text | F24: Update Table | G24: Insert Text | H24: D
... A29: 27 | B29: Word | C29: Show group includes | D29: Ruler | E29: Gridlines | F29: Navigation Pane | G29: All of These | H29: D
A30: 28 | B30: Word | C30: Navigation Pane provides _________ views by clicking on their respective tabs at the top of the Navigation Pane. | D30: 1 | E30: 2 | F30: 3 | G30: 4 | H30: C
A31: 29 | B31: Word | C31: _________ is a series of commands that we can use to automate a repeated task and can be run when we have to perform the task. | D31: Macro | E31: Consolidation | F31: What if Analyse | G31: None | H31: A
A32: 30 | B32: Word | C32: While Naming a Macro user cannot use | D32: Space | E32: @ | F32: % | G32: All of These | H32: D
A33: SECTION: POWERPOINT
A34: 31 | B34: PowerPoint | C34: Which of the following Tab is not avalibale in Ms-PowerPoint? | D34: Home | E34: Page Layout | F34: View | G34: Design | H34: B
A35: 32 | B35: PowerPoint | C35: Which tab is not available on left panel when you open a presentation? | D35: Outline | E35: Slides | F35: Notes | G35: All of the above | H35: C
A36: 33 | B36: PowerPoint | C36: PowerPoint presentations are widely used as | D36: Note outlines for teachers | E36: Project presentations by students | F36: Communication of planning | G36: All of the above | H36: D
A37: 34 | B37: PowerPoint | C37: In slide layout panel how many layouts are available for text layout by default? | D37: 4 | E37: 7 | F37: 12 | G37: None of the above | H37: A
A38: 35 | B38: PowerPoint | C38: What PowerPoint feature will you use to apply motion effects to objects? | D38: Slide Transition | E38: Slide Design | F38: Animation Objects | G38: Animation Scheme | H38: D
A39: 36 | B39: PowerPoint | C39: What feature will you use to apply motion effects in slide transitions? | D39: Slide Transition | E39: Slide Design | F39: Animation Objects | G39: Animation Scheme | H39: A
A40: 37 | B40: PowerPoint | C40: _________ is a template used to create consistent layouts throughout the MS PowerPoint presentation. | D40: Notes Master | E40: Slide Master | F40: Handout Master | G40: Clip Art | H40: B
A41: 38 | B41: PowerPoint | C41: In MS-PowerPoint, Default Page Orientation is | D41: Portrait | E41: Landscape | F41: Both A and B | G41: NONE | H41: B
A42: 39 | B42: PowerPoint | C42: Want your logo in the same position on every slide, automatically, Insert it on the _________ in PowerPoint. | D42: Handout master | E42: Notes master | F42: Slide master | G42: All of the above | H42: C
A43: 40 | B43: PowerPoint | C43: Objects on the slide that hold text are called | D43: Placeholders | E43: Object holders | F43: Auto layouts | G43: Text holders | H43: A
A44: 41 | B44: PowerPoint | C44: Which of the following group is not avalibale in Home tab of Ms-PowerPoint? | D44: Clipboard | E44: Slides | F44: Alignment | G44: Font | H44: C
A45: 42 | B45: PowerPoint | C45: _________ is use to apply formatting from text, shapes and pictures to another selection in Ms-PowerPoint. | D45: Format Painter | E45: Copy | F45: Styles | G45: None of the above | H45: A
A46: 43 | B46: PowerPoint | C46: How many groups we have in Insert tab of Ms-PowerPoint? | D46: 6 | E46: 7 | F46: 8 | G46: 9 | H46: B
A47: 44 | B47: PowerPoint | C47: In PowerPoint, you can use _________ to launch any other Presentation, Application or Website from your presentation. | D47: Styles | E47: Action button | F47: Object Linking | G47: None of the above | H47: B
A48: 45 | B48: PowerPoint | C48: You can modify the background of a PowerPoint presentation by using _________ Tab. | D48: Design | E48: Insert | F48: Transitions | G48: Slide Show | H48: A
A49: 46 | B49: PowerPoint | C49: What is a motion path in PowerPoint? | D49: A type of animation entrance effect | E49: A method of advancing slides | F49: A method of moving items on a slide | G49: All of the above | H49: C
A50: 47 | B50: PowerPoint | C50: The special effects used to introduce slides in a presentation are called _________ in PowerPoint. | D50: Effects | E50: Custom animations | F50: Transitions | G50: Present animations | H50: C
A51: 48 | B51: PowerPoint | C51: Which of the following should you use if you want all the slide in the presentation to have the same "look"? | D51: The slide layout option | E51: Add a slide option | F51: Outline view | G51: A presentation design template | H51: D
A52: 49 | B52: PowerPoint | C52: In order to edit a chart in PowerPoint, you can | D52: Delete and create new | E52: Click and drag the chart object | F52: Double click the chart object | G52: Click the chart object | H52: C
A53: 50 | B53: PowerPoint | C53: Which by default theme was appliyed on the slides in Ms-PowerPoint? | D53: Apex Theme | E53: Office Theme | F53: Angels Theme | G53: None of the above | H53: B
A54: 51 | B54: PowerPoint | C54: Slide Orientation option available in which group of Design tab in PowerPoint? | D54: Themes | E54: Background | F54: Page Setup | G54: Page Layout | H54: C
A55: 52 | B55: PowerPoint | C55: How the information is arranged on the slide is controlled by _________ in PowerPoint? | D55: Slide layouts | E55: Background | F55: Themes | G55: Slide Master | H55: A
A56: 53 | B56: PowerPoint | C56: The presentation inherits various design elements as well as prewritten content that's stored in the template called _________ | D56: Background | E56: Slide layouts | F56: Themes | G56: Effects | H56: C
A57: 54 | B57: PowerPoint | C57: Slide layout option available in _________ group of Home tab in Ms-PowePoint. | D57: Slides | E57: Font | F57: Editing | G57: Clipboard | H57: A
A58: 55 | B58: PowerPoint | C58: The Powerpoint presentation can be saved using the shortcut key. | D58: Ctrl+S | E58: Shift+F12 | F58: Both A & B | G58: Ctrl+F3 | H58: C
... A60: 57 | B60: PowerPoint | C60: Which of them is not a part of PowerPoint Ribbon? | D60: Home | E60: Design | F60: Tool | G60: Slide Show | H60: C
A61: 58 | B61: PowerPoint | C61: By default, Save, Undo and Redo appear on the Quick Access Toolbar | D61: TRUE | E61: FALSE | H61: A
A62: 59 | B62: PowerPoint | C62: The very bottom of the screen is the _________ which tells about the slide that is currently displayed. | D62: Notes | E62: Status bar | F62: Task Bar | G62: Navigation Pane | H62: B
A63: 60 | B63: PowerPoint | C63: What is the Shortcut key of Hyperlink in Ms-PowerPoint? | D63: Ctrl+H | E63: Ctrl+L | F63: Ctrl+K | G63: None | H63: C
A64: SECTION: EXCEL
A65: 61 | B65: Excel | C65: What is the default row height in Excel? | D65: 12.75 | E65: 15 | F65: 20 | G65: 25 | H65: A
A66: 62 | B66: Excel | C66: Which of the following charts is best for showing trends over time? | D66: Pie Chart | E66: Line Chart | F66: Bar Chart | G66: Scatter Plot | H66: B
A67: 63 | B67: Excel | C67: How do you freeze the top row in Excel? | D67: View > Freeze Panes > Freeze Top Row | E67: Insert > Freeze Top Row | F67: Data > Freeze Top Row | G67: File > Freeze Top Row | H67: A
A68: 64 | B68: Excel | C68: Which of the following is not a valid data type in Excel? | D68: Number | E68: Text | F68: Picture | G68: Date | H68: C
A69: 65 | B69: Excel | C69: Which Excel function will display the current date? | D69: NOW() | E69: DATE() | F69: TODAY() | G69: CURRENT() | H69: C
A70: 66 | B70: Excel | C70: Which chart type is best for comparing parts of a whole? | D70: Bar Chart | E70: Pie Chart | F70: Line Chart | G70: Area Chart | H70: B
A71: 67 | B71: Excel | C71: How do you remove the content of a cell in Excel? | D71: Press Delete | E71: Press Backspace | F71: Right-click and choose Clear Contents | G71: All of the above | H71: D
A72: 68 | B72: Excel | C72: What is the purpose of the TEXT function in Excel? | D72: To convert a number to text | E72: To change the font style | F72: To extract text from a string | G72: To combine text from multiple cells | H72: A
A73: 69 | B73: Excel | C73: Which of the following is a valid cell reference in Excel? | D73: A1 | E73: 1A | F73: AA1 | G73: Both A and C | H73: D
A74: 70 | B74: Excel | C74: Which function will return the number of characters in a text string? | D74: LEN() | E74: LENGTH() | F74: COUNT() | G74: CHAR() | H74: A
A75: 71 | B75: Excel | C75: How do you insert a comment in an Excel cell? | D75: Review > New Comment | E75: Home > New Comment | F75: Insert > New Comment | G75: Data > New Comment | H75: A
A76: 72 | B76: Excel | C76: How do you highlight cells that meet a specific condition? | D76: Use Conditional Formatting | E76: Use Data Validation | F76: Use Format Painter | G76: Use Sorting | H76: A
A77: 73 | B77: Excel | C77: Which of the following is not a type of Sparkline in Excel? | D77: Line | E77: Column | F77: Win/Loss | G77: Bar | H77: D
... A101: 97 | B101: Excel | C101: We can use the feature of Custom Conditional formatting based on a _________ | D101: Value Fields | E101: Formula | F101: Both | G101: None | H101: B
A102: 98 | B102: Excel | C102: The data in a PivotTable cannot be changed as it is a summarized view of other data. | D102: TRUE | E102: FALSE | H102: A
A103: 99 | B103: Excel | C103: Excel offer upto _________ sort levels. | D103: Three | E103: Four | F103: Thirty-Six | G103: Sixty-Four | H103: D
A104: 100 | B104: Excel | C104: In Advanced Filter Criteria listed on the same row work with the _________ | D104: OR logic | E104: AND logic | F104: XOR logic | G104: XAND logic | H104: B
A105: 101 | B105: Excel | C105: Which type of _________ are used to display trends over time. | D105: Line charts | E105: Bar charts | F105: Column charts | G105: Any | H105: A
A106: 102 | B106: Excel | C106: IRR function represents | D106: The internal rate of return for a series of cash flows | E106: The interest rate of return for a series of cash flows | F106: The internal return of rate for a series of cash flows | G106: Any information | H106: A
A107: 103 | B107: Excel | C107: Goal Seek is a powerful tool for finding the _________ needed to achieve a specific goal | D107: input value | E107: output value | F107: data | G107: Any | H107: A
A108: 104 | B108: Excel | C108: Data Tables allow you to perform a one-variable or two-variable analysis of a formula | D108: Goal Seek | E108: Solver | F108: Data Tables | G108: Pivot Tables | H108: C
A109: 105 | B109: Excel | C109: By using Goal Seek, we can quickly determine _________ we are required to achieve | D109: the source | E109: the target | F109: Both Source & target | G109: None | H109: B
A110: 106 | B110: Excel | C110: Scenario Manager in Excel is particularly useful for | D110: Organizing data in a structured manner | E110: Creating and comparing different scenarios based on various input values | F110: Calculating financial functions | G110: Sorting data based on specific criteria | H110: B
A111: 107 | B111: Excel | C111: Which financial function in Excel calculates the future value of an investment? | D111: PV | E111: FV | F111: NPV | G111: IRR | H111: B
A112: 108 | B112: Excel | C112: What is the purpose of building a financial model in Excel? | D112: To perform basic calculations in a spreadsheet | E112: To create data visualizations | F112: To evaluate investment opportunities and conduct financial analysis | G112: To sort and filter data efficiently | H112: C
A113: 109 | B113: Excel | C113: Which Excel tool allows you to create and compare different scenarios based on various input values? | D113: Goal Seek | E113: Scenario Manager | F113: Data Tables | G113: Pivot Tables | H113: B
A114: 110 | B114: Excel | C114: What is the primary purpose of Ms-Excel in accounting finance, and data analysis? | D114: Create graphics | E114: Edit images | F114: Analyze numerical and financial data | G114: Write documents | H114: C
... A118: 114 | B118: Excel | C118: _________ enables the quick population of cells with patterns. | D118: Conditional Formatting | E118: AutoFill | F118: Flash Fill | G118: Paste | H118: B
A119: 115 | B119: Excel | C119: Conditional formatting introduces an intelligent layer to data visualization. | D119: TRUE | E119: FALSE | H119: A
A120: 116 | B120: Excel | C120: _________ enables you to automatically highlight cells that meet criteria, making key insights easily discernible. | D120: Conditional Formatting | E120: Formatting | F120: AutoFill | G120: Flash Fill | H120: A
A121: 117 | B121: Excel | C121: Which tab contains the feature 'Conditional Formatting'? | D121: Data Tab only | E121: Home Tab only | F121: Both A & B | G121: None | H121: B
A122: 118 | B122: Excel | C122: To rotate text for better fit, use the dropdown and choose an angle. | D122: Wrap Text | E122: Indentation | F122: Orientation | G122: Organization | H122: C
A123: 119 | B123: Excel | C123: Maintaining consistency in formatting is essential for professional-looking worksheets. | D123: Format as Table | E123: Pivot Table | F123: Data Table | G123: Cell styles and themes | H123: D
A124: 120 | B124: Excel | C124: _________ quickly converts a range of cells to a table with its own style. | D124: Format as Table | E124: Cell styles and themes | F124: Pivot Table | G124: Data Table | H124: A
A125: 121 | B125: Excel | C125: _________ combine and center the contents of the selected cells in a new larger cell. | D125: Wrap Text | E125: Merge & Center | F125: Paste Special | G125: Text to Column | H125: B
A126: 122 | B126: Excel | C126: Which tab is used to access cell alignment and orientation options in excel? | D126: Home | E126: Insert | F126: Format | G126: View | H126: A
A127: 123 | B127: Excel | C127: What does filtering allow you to do in a table? | D127: Display specific data based on chosen criteria | E127: Add new rows to the table | F127: Change the table style | G127: Convert the table back to a range | H127: A
A128: 124 | B128: Excel | C128: How can you merge and center cells in Excel? | D128: Format Tab > Merge Cells | E128: Home Tab > Merge & Center dropdown | F128: Right-click on cells and choose "Merge" | G128: Press CTRL + M on the keyboard | H128: B
A129: 125 | B129: Excel | C129: Default row height & width of a cell? | D129: 15.43 & 8.15 | E129: 8.15 & 15.43 | F129: 15 & 8.43 | G129: 8 & 15 | H129: C
A130: 126 | B130: Excel | C130: Total rows & columns of a worksheet are _________ | D130: 1000000 & 16000 | E130: 10000 & 16000 | F130: 1040000 & 16300 | G130: 1048576 & 16384 | H130: D
A131: 127 | B131: Excel | C131: =$A$1 is the example of _________ | D131: Relative References | E131: Absolute References | F131: Mixed References | G131: Natural Cell Reference | H131: B
...
